bitcoinhisyprice/__init__.py
bitcoinhisyprice/client.py
bitcoinhisyprice/core.py
bitcoinhisyprice-0.0.1.dist-info/DESCRIPTION.rst
bitcoinhisyprice-0.0.1.dist-info/METADATA
bitcoinhisyprice-0.0.1.dist-info/RECORD
bitcoinhisyprice-0.0.1.dist-info/WHEEL
bitcoinhisyprice-0.0.1.dist-info/metadata.json
bitcoinhisyprice-0.0.1.dist-info/top_level.txt
