Metadata-Version: 2.0
Name: bitcoinhisyprice
Version: 0.0.1
Summary: A package to retrive bitcoin history price data from coin market cap
Home-page: https://github.com/leoacan/bitcoinhisyprice.git
Author: UNKNOWN
Author-email: xucanc2@gmail.com
License: UNKNOWN
Platform: UNKNOWN
Classifier: Programming Language :: Python :: 3
Classifier: License :: OSI Approved :: MIT License
Classifier: Operating System :: OS Independent
Requires-Dist: bs4 (>=0.01)
Requires-Dist: requests (>=2.18.4)
Requires-Dist: requests-cache (>=0.4.13)
